pypi_test1-1.1.14.dist-info/licenses/LICENSE
safeheron_api_sdk_python/client.py
safeheron_api_sdk_python/tools.py
safeheron_api_sdk_python/api/account_api.py
safeheron_api_sdk_python/api/coin_api.py
safeheron_api_sdk_python/api/mpc_sign_api.py
safeheron_api_sdk_python/api/transaction_api.py
safeheron_api_sdk_python/api/web3_api.py
safeheron_api_sdk_python/api/webhook_api.py
safeheron_api_sdk_python/api/whitelist_api.py
safeheron_api_sdk_python/cosigner/co_signer_converter.py
safeheron_api_sdk_python/webhook/webhook_converter.py
pypi_test1-1.1.14.dist-info/METADATA
pypi_test1-1.1.14.dist-info/WHEEL
pypi_test1-1.1.14.dist-info/top_level.txt
pypi_test1-1.1.14.dist-info/RECORD
